m_abac/__init__.py
m_abac/call_api.py
m_abac/pdp.py
m_abac/result_access.py
m_abac/adapter/__init__.py
m_abac/adapter/adapter.py
m_abac/adapter/elasticsearch_adapter.py
m_abac/policy/__init__.py
m_abac/policy/exceptions.py
m_abac/policy/policy.py
m_abac/policy/utils.py
m_abac/policy/conditions/__init__.py
m_abac/policy/conditions/base.py
m_abac/policy/conditions/schema.py
m_abac/policy/conditions/boolean/__init__.py
m_abac/policy/conditions/boolean/base.py
m_abac/policy/conditions/boolean/check_bool.py
m_abac/policy/conditions/collection/__init__.py
m_abac/policy/conditions/collection/all_in.py
m_abac/policy/conditions/collection/all_not_in.py
m_abac/policy/conditions/collection/any_in.py
m_abac/policy/conditions/collection/any_not_in.py
m_abac/policy/conditions/collection/base.py
m_abac/policy/conditions/collection/is_empty.py
m_abac/policy/conditions/collection/is_in.py
m_abac/policy/conditions/collection/is_not_empty.py
m_abac/policy/conditions/collection/is_not_in.py
m_abac/policy/conditions/date_time/__init__.py
m_abac/policy/conditions/date_time/base.py
m_abac/policy/conditions/date_time/date_eq.py
m_abac/policy/conditions/date_time/date_gt.py
m_abac/policy/conditions/date_time/date_gte.py
m_abac/policy/conditions/date_time/date_lt.py
m_abac/policy/conditions/date_time/date_lte.py
m_abac/policy/conditions/date_time/date_neq.py
m_abac/policy/conditions/day/__init__.py
m_abac/policy/conditions/day/base.py
m_abac/policy/conditions/day/day_eq.py
m_abac/policy/conditions/day/day_gt.py
m_abac/policy/conditions/day/day_gte.py
m_abac/policy/conditions/day/day_lt.py
m_abac/policy/conditions/day/day_lte.py
m_abac/policy/conditions/day/day_neq.py
m_abac/policy/conditions/ip_address/__init__.py
m_abac/policy/conditions/ip_address/base.py
m_abac/policy/conditions/ip_address/in_subnet.py
m_abac/policy/conditions/ip_address/not_in_subnet.py
m_abac/policy/conditions/numeric/__init__.py
m_abac/policy/conditions/numeric/base.py
m_abac/policy/conditions/numeric/eq.py
m_abc_anhnt-1.0.2.dist-info/METADATA
m_abc_anhnt-1.0.2.dist-info/WHEEL
m_abc_anhnt-1.0.2.dist-info/top_level.txt
m_abc_anhnt-1.0.2.dist-info/RECORD
