Metadata-Version: 2.1
Name: m-abc-anhnt
Version: 1.0.2
Summary: Thư viện xử lý kiểm tra quyền theo logic ABAC (Attribute-based access control)
Home-page: https://github.com/mobiovn
Author: MOBIO
Author-email: contact@mobio.vn
License: MIT
Project-URL: Source, https://github.com/mobiovn
Keywords: mobio,mobio-engine,m-abac
Classifier: Development Status :: 3 - Alpha
Classifier: Intended Audience :: Developers
Classifier: Topic :: Software Development :: Build Tools
Classifier: License :: OSI Approved :: MIT License
Classifier: Programming Language :: Python :: 3
Classifier: Programming Language :: Python :: 3.6
Classifier: Programming Language :: Python :: 3.7
Classifier: Programming Language :: Python :: 3.8
Classifier: Programming Language :: Python :: 3.9
Classifier: Programming Language :: Python :: 3 :: Only
Requires-Python: >=3
Requires-Dist: requests
Requires-Dist: marshmallow
Requires-Dist: marshmallow-oneofschema
Requires-Dist: ipaddress
Requires-Dist: objectpath
Requires-Dist: redis
Requires-Dist: m-caching
Requires-Dist: user-agents
Requires-Dist: Flask
